setup.py
distributions_gunjan_test/Binomialdistribution.py
distributions_gunjan_test/Gaussiandistribution.py
distributions_gunjan_test/Generaldistribution.py
distributions_gunjan_test/__init__.py
distributions_gunjan_test.egg-info/PKG-INFO
distributions_gunjan_test.egg-info/SOURCES.txt
distributions_gunjan_test.egg-info/dependency_links.txt
distributions_gunjan_test.egg-info/not-zip-safe
distributions_gunjan_test.egg-info/top_level.txt